{
  "id": "559edbf347cdaa075e000268",
  "title": "CeCILL Free Software License Agreement v1.0 (CECILL-1.0)",
  "manager": {
    "id": "558c1fd847cdaa075e000123",
    "username": "bfitzg"
  },
  "slug": "cecill-free-software-license-agreement-v1.0-(cecill-1.0)",
  "source": "https://tldrlegal.com/api/license/559edbf347cdaa075e000268",
  "description": "<p>A copyleft license in the spirit of and compatible with GNU GPL.&nbsp;</p>",
  "summary": {
    "must": [
      {
        "title": "Include Copyright",
        "description": "Describes whether the original copyright must be retained."
      },
      {
        "title": "Include License",
        "description": "Including the full text of license in modified software."
      },
      {
        "title": "Include Notice",
        "description": "Include a \"NOTICE\" file with attribution notes included."
      },
      {
        "title": "Disclose Source",
        "description": "Describes whether you must disclose your source code when you distribute the software."
      },
      {
        "title": "State Changes",
        "description": "Stating significant changes made to software."
      }
    ],
    "cannot": [],
    "can": [
      {
        "title": "Modify",
        "description": "Describes the ability to modify the software and create derivatives."
      },
      {
        "title": "Distribute",
        "description": "Describes the ability to distribute original or modified (derivative) works."
      },
      {
        "title": "Commercial Use",
        "description": "Describes the ability to use the software for commercial purposes."
      },
      {
        "title": "Hold Liable",
        "description": "Describes the warranty and if the software/license owner can be charged for damages."
      }
    ]
  },
  "fulltext": "<h1>FREE SOFTWARE LICENSING AGREEMENT CeCILL</h1><h2>Notice</h2><p>This Agreement is a free software license that is the result of discussions between its authors in order to ensure compliance with the two main principles guiding its drafting:</p><ul>\r\n<li>firstly, its conformity with French law, both as regards the law of torts and intellectual property law, and the protection that it offers to authors and the holders of economic rights over software.</li><li>secondly, compliance with the principles for the distribution of free software: access to source codes, extended user-rights.</li></ul><p>The following bodies are the authors of the license CeCILL<sup><a href=\"http://www.cecill.info/licences/Licence_CeCILL_V1-US.html#sdfootnote1sym\"><sup>1</sup></a></sup>:</p><p>Commissariat à l’Energie Atomique – CEA, a public scientific, technical and industrial establishment, having its principal place of business at 31-33 rue de la Fédération, 75752 PARIS cedex 15.</p><p>Centre National de la Recherche Scientifique – CNRS, a public scientific and technological establishment, having its principal place of business at 3 rue Michel-Ange 75794 Paris cedex 16.</p><p>Institut National de Recherche en Informatique et en Automatique– INRIA, a public scientific and technological establishment, having its principal place of business at Domaine de Voluceau, Rocquencourt, BP 105, 78153 Le Chesnay cedex.</p><h2>PREAMBLE</h2><p>The purpose of this Free Software Licensing Agreement is to grant users the right to modify and redistribute the software governed by this license within the framework of an “open source” distribution model.</p><p>The exercising of these rights is conditional upon certain obligations for users so as to ensure that this status is retained for subsequent redistribution operations.</p><p>Nevertheless, access to the source code, and the resulting rights to copy, modify and redistribute only provide users with a limited warranty and the software’s author, the holder of the economic rights, and the successive licensors only have limited liability.</p><p>In this respect, the user’s attention is drawn to the risks associated with loading, using, modifying and/or developing or reproducing the software by the user in light of its specific status of free software, that may mean that it is complicated to manipulate, and that also therefore means that it is reserved for developers and experienced professionals having in-depth IT knowledge. Users are therefore encouraged to load and test the Software’s suitability as regards their requirements in conditions enabling the security of their systems and/or data to be ensured and, more generally, to use and operate it in the same conditions as regards security. This Agreement may be freely reproduced and published, provided it is not altered, and that no Articles are either added or removed herefrom.</p><p>This Agreement may apply to any or all software for which the holder of the economic rights decides to submit the operation thereof to its provisions.</p><h3>Article 1 - DEFINITIONS</h3><p>For the purposes of this Agreement, when the following expressions commence with a capital letter, they shall have the following meaning:</p><p>Agreement: means this Licensing Agreement, and any or all of its subsequent versions.</p><p>Software: means the software in its Object Code and/or Source Code form and, where applicable, its documentation, “as is” at the time when the Licensee accepts the Agreement.</p><p>Initial Software: means the Software in its Source Code and/or Object Code form and, where applicable, its documentation, “as is” at the time when it is distributed for the first time under the terms and conditions of the Agreement.</p><p>Modified Software: means the Software modified by at least one Contribution.</p><p>Source Code: means all the Software’s instructions and program lines to which access is required so as to modify the Software.</p><p>Object Code: means the binary files originating from the compilation of the Source Code.</p><p>Holder: means the holder of the economic copyright over the Initial Software.</p><p>Licensee(s): mean(s) the Software user(s) having accepted the Agreement.</p><p>Contributor: means a Licensee having made at least one Contribution.</p><p>Licensor: means the Holder, or any or all other individual or legal entity, that distributes the Software under the Agreement.</p><p>Contributions: mean any or all modifications, corrections, translations, adaptations and/or new functionalities integrated into the Software by any or all Contributor, and the Static Modules.</p><p>Module: means a set of sources files including their documentation that, once compiled in executable form, enables supplementary functionalities or services to be developed in addition to those offered by the Software.</p><p>Dynamic Module: means any or all module, created by the Contributor, that is independent of the Software, so that this module and the Software are in two different executable forms that are run in separate address spaces, with one calling the other when they are run.</p><p>Static Module: means any or all module, created by the Contributor and connected to the Software by a static link that makes their object codes interdependent. This module and the Software to which it is connected, are combined in a single executable.</p><p>Parties: mean both the Licensee and the Licensor.</p><p>These expressions may be used both in singular and plural form.</p><h3>Article 2 - PURPOSE</h3><p>The purpose of the Agreement is to enable the Licensor to grant the Licensee, non-exclusive, transferable and worldwide License for the Software as set forth in Article 5 hereinafter for the whole term of protection of the rights over said Software.</p><h3>Article 3 - ACCEPTANCE</h3><p>3.1. The Licensee shall be deemed as having accepted the terms and conditions of this Agreement by the occurrence of the first of the following events:</p><ul><li>(i) loading the Software by any or all means, notably, by downloading from a remote server, or by loading from a physical medium;</li><li>(ii) the first time the Licensee exercises any of the rights granted hereunder.</li></ul><p>3.2. One copy of the Agreement, containing a notice relating to the specific nature of the Software, to the limited warranty, and to the limitation to use by experienced users has been provided to the Licensee prior to its acceptance as set forth in Article 3.1 hereinabove, and the Licensee hereby acknowledges that it is aware thereof.</p><h3>Article 4 - EFFECTIVE DATE AND TERM</h3><h4>4.1. EFFECTIVE DATE</h4><p>The Agreement shall become effective on the date when it is accepted by the Licensee as set forth in Article 3.1.</p><h4>4.2. TERM</h4><p>The Agreement shall remain in force during the whole legal term of protection of the economic rights over the Software.</p><h3>Article 5 - SCOPE OF THE RIGHTS GRANTED</h3><p>The Licensor hereby grants to the Licensee, that accepts such, the following rights as regards the Software for any or all use, and for the term of the Agreement, on the basis of the terms and conditions set forth hereinafter.</p><p>Otherwise, the Licensor grants to the Licensee free of charge exploitation rights on the patents he holds on whole or part of the inventions implemented in the Software.</p><h4>5.1. RIGHTS OF USE</h4><p>The Licensee is authorized to use the Software, unrestrictedly, as regards the fields of application, with it being hereinafter specified that this relates to:</p><ol><li>permanent or temporary reproduction of all or part of the Software by any or all means and in any or all form.</li><li>loading, displaying, running, or storing the Software on any or all medium.</li><li>entitlement to observe, study or test the operation thereof so as to establish the ideas and principles that form the basis for any or all constituent elements of said Software. This shall apply when the Licensee carries out any or all loading, displaying, running, transmission or storage operation as regards the Software, that it is entitled to carry out hereunder.</li></ol><h4>5.2. entitlement to make CONTRIBUTIONS</h4><p>The right to make Contributions includes the right to translate, adapt, arrange, or make any or all modification to the Software, and the right to reproduce the resulting Software.</p><p>The Licensee is authorized to make any or all Contribution to the Software provided that it explicitly mentions its name as the author of said Contribution and the date of the development thereof.</p><h4>5.3. DISTRIBUTION AND PUBLICATION RIGHTS</h4><p>In particular, the right of distribution and publication includes the right to transmit and communicate the Software to the general public on any or all medium, and by any or all means, and the right to market, either in consideration of a fee, or free of charge, a copy or copies of the Software by means of any or all process.</p><p>The Licensee is further authorized to redistribute copies of the modified or unmodified Software to third parties according to the terms and conditions set forth hereinafter.</p><h5>5.3.1. REDISTRIBUTIONOF SOFTWARE WITHOUT MODIFICATION</h5><p>The Licensee is authorized to redistribute true copies of the Software in Source Code or Object Code form, provided that said redistribution complies with all the provisions of the Agreement and is accompanied by:</p><ol><li>a copy of the Agreement,</li><li>a notice relating to the limitation of both the Licensor’s warranty and liability as set forth in Articles 8 and 9,</li></ol><p>and that, in the event that only the Software’s Object Code is redistributed, the Licensee allows future Licensees unhindered access to the Software’s full Source Code by providing them with the terms and conditions for access thereto, it being understood that the additional cost of acquiring the Source Code shall not exceed the cost of transferring the data.</p><h5>5.3.2. REDISTRIBUTION OF MODIFIED SOFTWARE</h5><p>When the Licensee makes a Contribution to the Software, the terms and conditions for the redistribution of the Modified Software shall then be subject to all the provisions hereof.</p><p>The Licensee is authorized to redistribute the Modified Software, in Source Code or Object Code form, provided that said redistribution complies with all the provisions of the Agreement and is accompanied by:</p><ol><li>a copy of the Agreement,</li><li>a notice relating to the limitation of both the Licensor’s warranty and liability as set forth in Articles 8 and 9,</li></ol><p>and that, in the event that only the Modified Software’s Object Code is redistributed, the Licensee allows future Licensees unhindered access to the Modified Software’s full Source Code by providing them with the terms and conditions for access thereto, it being understood that the additional cost of acquiring the Source Code shall not exceed the cost of transferring the data.</p><h5>5.3.3. REDISTRIBUTION OF DYNAMIC MODULES</h5><p>When the Licensee has developed a Dynamic Module, the terms and conditions hereof do not apply to said Dynamic Module, that may be distributed under a separate Licensing Agreement.</p><h5>5.3.4. COMPATIBILITY WITH THE GPL LICENSE</h5><p>In the event that the Modified or unmodified Software includes a code that is subject to the provisions of the GPL License, the Licensee is authorized to redistribute the whole under the GPL License.</p><p>In the event that the Modified Software includes a code that is subject to the provisions of the GPL License, the Licensee is authorized to redistribute the Modified Software under the GPL License.</p><h3>Article 6 - INTELLECTUAL PROPERTY OVER THE INITIAL SOFTWARE</h3><h4>6.1. OVER THE INITIAL SOFTWARE</h4><p>The Holder owns the economic rights over the Initial Software. Any or all use of the Initial Software is subject to compliance with the terms and conditions under which the Holder has elected to distribute its work and no one shall be entitled to modify the terms and conditions for the distribution of said Initial Software.</p><p>The Holder undertakes to maintain the distribution of the Initial Software under the conditions of the Agreement, for the duration set forth in article 4.2.</p><h4>6.2. OVER THE CONTRIBUTIONS</h4><p>The intellectual property rights over the Contributions are attached to the holder of the economic rights as designated by effective legislation.</p><h4>6.3. OVER THE DYNAMIC MODULES</h4><p>The Licensee having developed a Dynamic Module is the holder of the intellectual property rights over said Dynamic Module and is free to choose the agreement that shall govern its distribution.</p><h4>6.4. JOINT PROVISIONS</h4><p>6.4.1. The Licensee expressly undertakes:</p><ol><li>not to remove, or modify, in any or all manner, the intellectual property notices affixed to the Software;</li><li>to reproduce said notices, in an identical manner, in the copies of the Software.</li></ol><p>6.4.2. The Licensee undertakes not to directly or indirectly infringe the intellectual property rights of the Holder and/or Contributors and to take, where applicable, vis-à-vis its staff, any or all measures required to ensure respect for said intellectual property rights of the Holder and/or Contributors.</p><h3>Article 7 - RELATED SERVICES</h3><p>7.1. Under no circumstances shall the Agreement oblige the Licensor to provide technical assistance or maintenance services for the Software.</p><p>However, the Licensor is entitled to offer this type of service. The terms and conditions of such technical assistance, and/or such maintenance, shall then be set forth in a separate instrument. Only the Licensor offering said maintenance and/or technical assistance services shall incur liability therefor.</p><p>7.2. Similarly, any or all Licensor shall be entitled to offer to its Licensees, under its own responsibility, a warranty, that shall only be binding upon itself, for the redistribution of the Software and/or the Modified Software, under terms and conditions that it shall decide upon itself. Said warranty, and the financial terms and conditions of its application, shall be subject to a separate instrument executed between the Licensor and the Licensee.</p><h3>Article 8 - LIABILITY</h3><p>8.1. Subject to the provisions of Article 8.2, should the Licensor fail to fulfill all or part of its obligations hereunder, the Licensee shall be entitled to claim compensation for the direct loss suffered that it is able to justify, subject to providing proof of negligence by the Licensor in question.</p><p>8.2. The Licensor’s liability is limited to the commitments made under this Agreement and shall not be incurred as a result , in particular: (i) of loss due the Licensee’s total or partial failure to fulfill its obligations, (ii) direct or consequential loss due to the Software’s use or performance that is suffered by the Licensee, when the latter is a professional using said Software for professional purposes and (iii) consequential loss due to the Software’s use or performance. The Parties expressly agree that any or all pecuniary or business loss (i.e. loss of data, loss of profits, operating loss, loss of customers or orders, opportunity cost, any disturbance to business activities) or any or all legal proceedings instituted against the Licensee by a third party, shall constitute consequential loss and shall not provide entitlement to any or all compensation from the Licensor.</p><h3>Article 9 - WARRANTY</h3><p>9.1. The Licensee acknowledges that the current situation as regards scientific and technical know-how at the time when the Software was distributed did not enable all possible uses to be tested and verified, nor for the presence of any or all faults to be detected. In this respect, the Licensee’s attention has been drawn to the risks associated with loading, using, modifying and/or developing and reproducing the Software that are reserved for experienced users.</p><p>The Licensee shall be responsible for verifying, by any or all means, the product’s suitability for its requirements, its due and proper functioning, and for ensuring that it shall not cause damage to either persons or property.</p><p>9.2. The Licensor hereby represents, in good faith, that it is entitled to grant all the rights on the Software (including in particular the rights set forth in Article 5).</p><p>9.3. The Licensee acknowledges that the Software is supplied “as is” by the Licensor without any or all other express or tacit warranty, other than that provided for in Article 9.2 and, in particular, without any or all warranty as to its market value, its securised, innovative or relevant nature.</p><p>Specifically, the Licensor does not warrant that the Software is free from any or all error, that it shall operate continuously, that it shall be compatible with the Licensee’s own equipment and its software configuration, nor that it shall meet the Licensee’s requirements.</p><p>9.4 The Licensor does not either expressly or tacitly warrant that the Software does not infringe any or all third party intellectual right relating to a patent, software or to any or all other property right. Moreover, the Licensor shall not hold the Licensee harmless against any or all proceedings for infringement that may be instituted in respect of the use, modification and redistribution of the Software. Nevertheless, should such proceedings be instituted against the Licensee, the Licensor shall provide it with technical and legal assistance for its defense. Such technical and legal assistance shall be decided upon on a case-by-case basis between the relevant Licensor and the Licensee pursuant to a memorandum of understanding. The Licensor disclaims any or all liability as regards the Licensee’s use of the Software’s name. No warranty shall be provided as regards the existence of prior rights over the name of the Software and as regards the existence of a trademark.</p><h3>Article 10 - TERMINATION</h3><p>10.1. In the event of a breach by the Licensee of its obligations hereunder, the Licensor may automatically terminate this Agreement thirty (30) days after notice has been sent to the Licensee and has remained ineffective.</p><p>10.2. The Licensee whose Agreement is terminated shall no longer be authorized to use, modify or distribute the Software. However, any or all licenses that it may have granted prior to termination of the Agreement shall remain valid subject to their having been granted in compliance with the terms and conditions hereof.</p><h3>Article 11 - MISCELLANEOUS PROVISIONS</h3><h4>11.1. EXCUSABLE EVENTS</h4><p>Neither Party shall be liable for any or all delay, or failure to perform the Agreement, that may be attributable to an event of force majeure, an act of God or an outside cause, such as, notably, defective functioning, or interruptions affecting the electricity or telecommunications networks, blocking of the network following a virus attack, the intervention of the government authorities, natural disasters, water damage, earthquakes, fire, explosions, strikes and labor unrest, war, etc.</p><p>11.2. The fact that either Party may fail, on one or several occasions, to invoke one or several of the provisions hereof, shall under no circumstances be interpreted as being a waiver by the interested Party of its entitlement to invoke said provision(s) subsequently.</p><p>11.3. The Agreement cancels and replaces any or all previous agreement, whether written or oral, between the Parties and having the same purpose, and constitutes the entirety of the agreement between said Parties concerning said purpose. No supplement or modification to the terms and conditions hereof shall be effective as regards the Parties unless it is made in writing and signed by their duly authorized representatives.</p><p>11.4. In the event that one or several of the provisions hereof were to conflict with a current or future applicable act or legislative text, said act or legislative text shall take precedence, and the Parties shall make the necessary amendments so as to be in compliance with said act or legislative text. All the other provisions shall remain effective. Similarly, the fact that a provision of the Agreement may be null and void, for any reason whatsoever, shall not cause the Agreement as a whole to be null and void.</p><h4>11.5. LANGUAGE</h4><p>The Agreement is drafted in both French and English. In the event of a conflict as regards construction, the French version shall be deemed authentic.</p><h3>Article 12 - NEW VERSIONS OF THE AGREEMENT</h3><p>12.1. Any or all person is authorized to duplicate and distribute copies of this Agreement.</p><p>12.2. So as to ensure coherence, the wording of this Agreement is protected and may only be modified by the authors of the License, that reserve the right to periodically publish updates or new versions of the Agreement, each with a separate number. These subsequent versions may incorporate new problems encountered by the free software.</p><p>12.3. Any or all Software distributed under a given version of the Agreement may only be subsequently distributed under the same version of the Agreement or a subsequent version, subject to the provisions of article 5.3.4.</p><h3>Article 13 - GOVERNING LAW AND JURISDICTION</h3><p>13.1. The Agreement is governed by French law. The Parties agree to endeavor to settle the disagreements or disputes that may arise during the performance of the Agreement out-of-court.</p><p>13.2. In the absence of an out-of-court settlement within two (2) months as from their occurrence, and unless emergency proceedings are necessary, the disagreements or disputes shall be referred to the Paris Courts having jurisdiction, by the first Party to take action.</p><p><a href=\"http://www.cecill.info/licences/Licence_CeCILL_V1-US.html#sdfootnote1anc\">1</a> Ce: CEA, C: CNRS, I: INRIA, LL: Logiciel Libre</p><p>Version 1 of 06/21/2004</p>"
}